vaultwarden/__init__.py
vaultwarden/__version__.py
vaultwarden/clients/__init__.py
vaultwarden/clients/bitwarden.py
vaultwarden/clients/vaultwarden.py
vaultwarden/models/__init__.py
vaultwarden/models/bitwarden.py
vaultwarden/models/enum.py
vaultwarden/models/exception_models.py
vaultwarden/models/permissive_model.py
vaultwarden/models/sync.py
vaultwarden/utils/__init__.py
vaultwarden/utils/crypto.py
vaultwarden/utils/logger.py
vaultwarden/utils/string_cases.py
python_vaultwarden-1.0.4.dist-info/METADATA
python_vaultwarden-1.0.4.dist-info/WHEEL
python_vaultwarden-1.0.4.dist-info/licenses/LICENSE
python_vaultwarden-1.0.4.dist-info/RECORD
