Metadata-Version: 2.4
Name: python-vaultwarden
Version: 1.0.4
Summary: Admin Vaultwarden and Simple Bitwarden Python Client
Author-email: Lyonel Martinez <lyonel.martinez@numberly.com>, Mathis Ribet <mathis.ribet@numberly.com>
License-Expression: Apache-2.0
License-File: LICENSE
Classifier: Development Status :: 4 - Beta
Classifier: Environment :: Web Environment
Classifier: Intended Audience :: Developers
Classifier: License :: OSI Approved :: Apache Software License
Classifier: Operating System :: OS Independent
Classifier: Programming Language :: Python
Classifier: Programming Language :: Python :: 3
Classifier: Programming Language :: Python :: 3 :: Only
Classifier: Programming Language :: Python :: 3.10
Classifier: Programming Language :: Python :: 3.11
Classifier: Topic :: Internet :: WWW/HTTP
Classifier: Typing :: Typed
Requires-Python: >=3.10
Requires-Dist: hkdf>=0.0.3
Requires-Dist: httpx>=0.24.1
Requires-Dist: pycryptodome>=3.17.0
Requires-Dist: pydantic>=2.5.0
